{
	"result": [{
		"aliMemberId": 0,
		"currencySymbol": "US $",
		"id": 32761297715,
		"image350Path": "https://ae01.alicdn.com/kf/HTB1qcNWOXXXXXXbaFXXq6xXFXXXB.jpg_350x350.jpg",
		"itemAlgInfo": "predata,pageIndex:3,",
		"lowerPrice": "10.44",
		"productDiscount": 0,
		"pvid": "c7c97523-1b36-41ea-99b0-ba0cd4263219",
		"saleInSixMonth": "342",
		"saleProductTotal": 0,
		"scm": "1007.14557.86615.0"
	}, {
		"aliMemberId": 0,
		"currencySymbol": "US $",
		"id": 32795521976,
		"image350Path": "https://ae01.alicdn.com/kf/HTB1VkIGSFXXXXXqXFXXq6xXFXXX1.jpg_350x350.jpg",
		"itemAlgInfo": "cartwish_predata,pageIndex:3,",
		"lowerPrice": "106.3",
		"productDiscount": 0,
		"pvid": "c7c97523-1b36-41ea-99b0-ba0cd4263219",
		"saleInSixMonth": "2064",
		"saleProductTotal": 0,
		"scm": "1007.14557.86615.0"
	}, {
		"aliMemberId": 0,
		"currencySymbol": "US $",
		"id": 32611839393,
		"image350Path": "https://ae01.alicdn.com/kf/HTB1lXrGLFXXXXblXFXXq6xXFXXXn.jpg_350x350.jpg",
		"itemAlgInfo": "predata,pageIndex:3,",
		"lowerPrice": "8.0",
		"productDiscount": 0,
		"pvid": "c7c97523-1b36-41ea-99b0-ba0cd4263219",
		"saleInSixMonth": "1363",
		"saleProductTotal": 0,
		"scm": "1007.14557.86615.0"
	}, {
		"aliMemberId": 0,
		"currencySymbol": "US $",
		"id": 32439148121,
		"image350Path": "https://ae01.alicdn.com/kf/HTB16ZVJJXXXXXanXpXXq6xXFXXXI.jpg_350x350.jpg",
		"itemAlgInfo": "predata,pageIndex:3,",
		"lowerPrice": "13.99",
		"productDiscount": 0,
		"pvid": "c7c97523-1b36-41ea-99b0-ba0cd4263219",
		"saleInSixMonth": "99",
		"saleProductTotal": 0,
		"scm": "1007.14557.86615.0"
	}, {
		"aliMemberId": 0,
		"currencySymbol": "US $",
		"id": 32819333846,
		"image350Path": "https://ae01.alicdn.com/kf/HTB11v8iSXXXXXXIXXXXq6xXFXXXC.jpg_350x350.jpg",
		"itemAlgInfo": "predata,pageIndex:3,",
		"lowerPrice": "25.87",
		"productDiscount": 0,
		"pvid": "c7c97523-1b36-41ea-99b0-ba0cd4263219",
		"saleInSixMonth": "11",
		"saleProductTotal": 0,
		"scm": "1007.14557.86615.0"
	}, {
		"aliMemberId": 0,
		"currencySymbol": "US $",
		"id": 32780529968,
		"image350Path": "https://ae01.alicdn.com/kf/HTB17AUWOFXXXXXSaXXXq6xXFXXX4.jpg_350x350.jpg",
		"itemAlgInfo": "predata,pageIndex:3,",
		"lowerPrice": "21.99",
		"productDiscount": 0,
		"pvid": "c7c97523-1b36-41ea-99b0-ba0cd4263219",
		"saleInSixMonth": "186",
		"saleProductTotal": 0,
		"scm": "1007.14557.86615.0"
	}, {
		"aliMemberId": 0,
		"currencySymbol": "US $",
		"id": 32819850723,
		"image350Path": "https://ae01.alicdn.com/kf/HTB1yvHVJVXXXXaSXXXXq6xXFXXXO.jpg_350x350.jpg",
		"itemAlgInfo": "predata,pageIndex:3,",
		"lowerPrice": "8.09",
		"productDiscount": 0,
		"pvid": "c7c97523-1b36-41ea-99b0-ba0cd4263219",
		"saleInSixMonth": "22",
		"saleProductTotal": 0,
		"scm": "1007.14557.86615.0"
	}, {
		"aliMemberId": 0,
		"currencySymbol": "US $",
		"id": 32629615724,
		"image350Path": "https://ae01.alicdn.com/kf/HTB16hJaMXXXXXb4XFXXq6xXFXXXG.jpg_350x350.jpg",
		"itemAlgInfo": "predata,pageIndex:3,",
		"lowerPrice": "6.39",
		"productDiscount": 0,
		"pvid": "c7c97523-1b36-41ea-99b0-ba0cd4263219",
		"saleInSixMonth": "1405",
		"saleProductTotal": 0,
		"scm": "1007.14557.86615.0"
	}, {
		"aliMemberId": 0,
		"currencySymbol": "US $",
		"id": 32753472025,
		"image350Path": "https://ae01.alicdn.com/kf/HTB1WHRTNVXXXXbSXFXXq6xXFXXXm.jpg_350x350.jpg",
		"itemAlgInfo": "predata,pageIndex:3,",
		"lowerPrice": "29.9",
		"productDiscount": 0,
		"pvid": "c7c97523-1b36-41ea-99b0-ba0cd4263219",
		"saleInSixMonth": "104",
		"saleProductTotal": 0,
		"scm": "1007.14557.86615.0"
	}, {
		"aliMemberId": 0,
		"currencySymbol": "US $",
		"id": 32751804033,
		"image350Path": "https://ae01.alicdn.com/kf/HTB1FTVzSpXXXXamapXXq6xXFXXX0.jpg_350x350.jpg",
		"itemAlgInfo": "predata,pageIndex:3,",
		"lowerPrice": "35.65",
		"productDiscount": 0,
		"pvid": "c7c97523-1b36-41ea-99b0-ba0cd4263219",
		"saleInSixMonth": "44",
		"saleProductTotal": 0,
		"scm": "1007.14557.86615.0"
	}, {
		"aliMemberId": 0,
		"currencySymbol": "US $",
		"id": 32723695985,
		"image350Path": "https://ae01.alicdn.com/kf/HTB1llskMVXXXXcAapXXq6xXFXXX2.jpg_350x350.jpg",
		"itemAlgInfo": "predata,pageIndex:3,",
		"lowerPrice": "59.9",
		"productDiscount": 0,
		"pvid": "c7c97523-1b36-41ea-99b0-ba0cd4263219",
		"saleInSixMonth": "396",
		"saleProductTotal": 0,
		"scm": "1007.14557.86615.0"
	}, {
		"aliMemberId": 0,
		"currencySymbol": "US $",
		"id": 32817046186,
		"image350Path": "https://ae01.alicdn.com/kf/HTB1sN0HRVXXXXc3XFXXq6xXFXXXO.jpg_350x350.jpg",
		"itemAlgInfo": "cartwish_predata,pageIndex:3,",
		"lowerPrice": "20.88",
		"productDiscount": 0,
		"pvid": "c7c97523-1b36-41ea-99b0-ba0cd4263219",
		"saleInSixMonth": "25",
		"saleProductTotal": 0,
		"scm": "1007.14557.86615.0"
	}, {
		"aliMemberId": 0,
		"currencySymbol": "US $",
		"id": 32780295016,
		"image350Path": "https://ae01.alicdn.com/kf/HTB1rB95OFXXXXatXVXXq6xXFXXXA.jpg_350x350.jpg",
		"itemAlgInfo": "cartwish_predata,pageIndex:3,",
		"lowerPrice": "145.99",
		"productDiscount": 0,
		"pvid": "c7c97523-1b36-41ea-99b0-ba0cd4263219",
		"saleInSixMonth": "111",
		"saleProductTotal": 0,
		"scm": "1007.14557.86615.0"
	}, {
		"aliMemberId": 0,
		"currencySymbol": "US $",
		"id": 32819724532,
		"image350Path": "https://ae01.alicdn.com/kf/HTB1D665SpXXXXc.XFXXq6xXFXXXO.jpg_350x350.jpg",
		"itemAlgInfo": "predata,pageIndex:3,",
		"lowerPrice": "19.56",
		"productDiscount": 0,
		"pvid": "c7c97523-1b36-41ea-99b0-ba0cd4263219",
		"saleInSixMonth": "7",
		"saleProductTotal": 0,
		"scm": "1007.14557.86615.0"
	}, {
		"aliMemberId": 0,
		"currencySymbol": "US $",
		"id": 32620826630,
		"image350Path": "https://ae01.alicdn.com/kf/HTB1KLZiQFXXXXXRaXXXq6xXFXXXP.jpg_350x350.jpg",
		"itemAlgInfo": "cartwish_predata,pageIndex:3,",
		"lowerPrice": "7.19",
		"productDiscount": 0,
		"pvid": "c7c97523-1b36-41ea-99b0-ba0cd4263219",
		"saleInSixMonth": "38",
		"saleProductTotal": 0,
		"scm": "1007.14557.86615.0"
	}, {
		"aliMemberId": 0,
		"currencySymbol": "US $",
		"id": 32816563625,
		"image350Path": "https://ae01.alicdn.com/kf/HTB1ZwEiQFXXXXX2XpXXq6xXFXXXH.jpg_350x350.jpg",
		"itemAlgInfo": "cartwish_predata,pageIndex:3,",
		"lowerPrice": "8.13",
		"productDiscount": 0,
		"pvid": "c7c97523-1b36-41ea-99b0-ba0cd4263219",
		"saleInSixMonth": "148",
		"saleProductTotal": 0,
		"scm": "1007.14557.86615.0"
	}, {
		"aliMemberId": 0,
		"currencySymbol": "US $",
		"id": 32820067140,
		"image350Path": "https://ae01.alicdn.com/kf/HTB1RbrfRVXXXXclXpXXq6xXFXXXZ.jpg_350x350.jpg",
		"itemAlgInfo": "cartwish_predata,pageIndex:3,",
		"lowerPrice": "14.99",
		"productDiscount": 0,
		"pvid": "c7c97523-1b36-41ea-99b0-ba0cd4263219",
		"saleInSixMonth": "27",
		"saleProductTotal": 0,
		"scm": "1007.14557.86615.0"
	}, {
		"aliMemberId": 0,
		"currencySymbol": "US $",
		"id": 32822013273,
		"image350Path": "https://ae01.alicdn.com/kf/UTB8SE1LXHPJXKJkSafSq6yqUXXaM.jpg_350x350.jpg",
		"itemAlgInfo": "cartwish_predata,pageIndex:3,",
		"lowerPrice": "196.64",
		"productDiscount": 0,
		"pvid": "c7c97523-1b36-41ea-99b0-ba0cd4263219",
		"saleInSixMonth": "980",
		"saleProductTotal": 0,
		"scm": "1007.14557.86615.0"
	}, {
		"aliMemberId": 0,
		"currencySymbol": "US $",
		"id": 32381136980,
		"image350Path": "https://ae01.alicdn.com/kf/HTB1JqZ4OXXXXXbKapXXq6xXFXXXl.jpg_350x350.jpg",
		"itemAlgInfo": "realCntyHot,pageIndex:3,",
		"lowerPrice": "8.87",
		"productDiscount": 0,
		"pvid": "c7c97523-1b36-41ea-99b0-ba0cd4263219",
		"saleInSixMonth": "569",
		"saleProductTotal": 0,
		"scm": "1007.14557.86615.0"
	}, {
		"aliMemberId": 0,
		"currencySymbol": "US $",
		"id": 32799385589,
		"image350Path": "https://ae01.alicdn.com/kf/HTB1yYPbQXXXXXXWXVXXq6xXFXXX6.jpg_350x350.jpg",
		"itemAlgInfo": "realCntyHot,pageIndex:3,",
		"lowerPrice": "4.4",
		"productDiscount": 0,
		"pvid": "c7c97523-1b36-41ea-99b0-ba0cd4263219",
		"saleInSixMonth": "468",
		"saleProductTotal": 0,
		"scm": "1007.14557.86615.0"
	}],
	"param": {
		"commonItems": 20,
		"cookieId": "de3c78c2bccf44c78a8aa2702ad85a70",
		"country": "US",
		"firstItems": 30,
		"inspiSceneId": "1005",
		"isDeepClickTrace": false,
		"metisSceneId": "10002",
		"page": 3,
		"pageId": "277856_random_1503036375633",
		"realeaseTag": 0,
		"secondReq": true,
		"sessionid": "de3c78c2bccf44c78a8aa2702ad85a70",
		"streamId": "3ea9f1be17d349078f566d853354c41c2017081723",
		"userId": "231017024",
		"visitorId": "de3c78c2bccf44c78a8aa2702ad85a70"
	},
	"isCacheItem": true,
	"isSuccess": true
}